gimi9_geocoder/__init__.py
gimi9_geocoder/client.py
gimi9_geocoder/exceptions.py
gimi9_geocoder/models.py
gimi9_geocoder/pandas_utils.py
gimi9_geocoder/utils.py
gimi9_geocoder-0.1.0.dist-info/licenses/LICENSE
gimi9_geocoder-0.1.0.dist-info/METADATA
gimi9_geocoder-0.1.0.dist-info/WHEEL
gimi9_geocoder-0.1.0.dist-info/top_level.txt
gimi9_geocoder-0.1.0.dist-info/RECORD
