Metadata-Version: 2.4
Name: gimi9-geocoder
Version: 0.1.0
Summary: 한국 주소 지오코딩을 위한 Python 라이브러리 - Korean address geocoding library
Author-email: gisman <gisman@gmail.com>
License: MIT
Project-URL: Homepage, https://geocode.gimi9.com/
Project-URL: Repository, https://github.com/gisman/gimi9_geocoder
Keywords: geocoding,korean,addresses,api,pandas,geopandas,gis
Classifier: Development Status :: 4 - Beta
Classifier: Intended Audience :: Developers
Classifier: Topic :: Scientific/Engineering :: GIS
Classifier: Topic :: Software Development :: Libraries :: Python Modules
Classifier: Programming Language :: Python :: 3
Classifier: Programming Language :: Python :: 3.8
Classifier: Programming Language :: Python :: 3.9
Classifier: Programming Language :: Python :: 3.10
Classifier: Programming Language :: Python :: 3.11
Classifier: Programming Language :: Python :: 3.12
Classifier: Operating System :: OS Independent
Requires-Python: >=3.8
License-File: LICENSE
Requires-Dist: httpx>=0.24.0
Requires-Dist: pandas>=1.3.0
Requires-Dist: geopandas>=0.10.0
Requires-Dist: shapely>=1.8.0
Provides-Extra: dev
Requires-Dist: pytest>=6.0; extra == "dev"
Requires-Dist: pytest-cov>=2.0; extra == "dev"
Requires-Dist: black>=22.0; extra == "dev"
Requires-Dist: flake8>=4.0; extra == "dev"
Requires-Dist: twine>=4.0; extra == "dev"
Requires-Dist: build>=0.7.0; extra == "dev"
Dynamic: license-file
